byzerperf/__init__.py
byzerperf/perf.py
byzerperf/utils.py
byzerperf/version.py
byzerperf-0.1.2.dist-info/METADATA
byzerperf-0.1.2.dist-info/WHEEL
byzerperf-0.1.2.dist-info/top_level.txt
byzerperf-0.1.2.dist-info/RECORD
