Metadata-Version: 2.1
Name: byzerperf
Version: 0.1.2
Summary: ByzerPerf: Byzer Perf
Author: allwefantasy
Classifier: Topic :: Scientific/Engineering :: Artificial Intelligence
Classifier: Programming Language :: Python :: 3.9
Classifier: Programming Language :: Python :: 3.10
